LICENSE
setup.py
pybd_gui/__init__.py
pybd_gui/actuator_or_sensor_chooser.py
pybd_gui/add_block_dialog.py
pybd_gui/edit_blocks_dialog.py
pybd_gui/input_chooser.py
pybd_gui/input_viewer.py
pybd_gui/loop_assigner.py
pybd_gui/menu_params_dialog.py
pybd_gui/multi_block_selector.py
pybd_gui/place_block_dialog.py
pybd_gui/placement_viewer.py
pybd_gui/tkinter_utils.py
pybd_gui.egg-info/PKG-INFO
pybd_gui.egg-info/SOURCES.txt
pybd_gui.egg-info/dependency_links.txt
pybd_gui.egg-info/requires.txt
pybd_gui.egg-info/top_level.txt