Metadata-Version: 2.1
Name: pybd_gui
Version: 1.4.5
Summary: gui front end for the modeling controls block diagrams in python
Home-page: https://github.com/ryanGT/pybd_gui
Author: Ryan Krauss
Author-email: ryanwkrauss@gmail.com
Classifier: Programming Language :: Python :: 3
Classifier: License :: OSI Approved :: MIT License
Classifier: Operating System :: OS Independent
License-File: LICENSE
Requires-Dist: py_block_diagram
Requires-Dist: krauss_misc
